DHCstat/__init__.py
DHCstat/_version.py
DHCstat/datamining.py
DHCstat/statistics.py
DHCstat-0.1.1.dist-info/DESCRIPTION.rst
DHCstat-0.1.1.dist-info/METADATA
DHCstat-0.1.1.dist-info/RECORD
DHCstat-0.1.1.dist-info/WHEEL
DHCstat-0.1.1.dist-info/entry_points.txt
DHCstat-0.1.1.dist-info/metadata.json
DHCstat-0.1.1.dist-info/top_level.txt
DHCstat-0.1.1.dist-info/zip-safe
